nonebot_plugin_gspanel/__init__.py
nonebot_plugin_gspanel/__utils__.py
nonebot_plugin_gspanel/__version__.py
nonebot_plugin_gspanel/data_convert.py
nonebot_plugin_gspanel/data_source.py
nonebot_plugin_gspanel/data_updater.py
nonebot_plugin_gspanel-0.2.25.dist-info/LICENSE
nonebot_plugin_gspanel-0.2.25.dist-info/METADATA
nonebot_plugin_gspanel-0.2.25.dist-info/WHEEL
nonebot_plugin_gspanel-0.2.25.dist-info/RECORD
