Metadata-Version: 2.1
Name: nonebot-plugin-gspanel
Version: 0.2.25
Summary: Genshin player cards plugin for NoneBot2
Home-page: https://github.com/monsterxcn/nonebot-plugin-gspanel
License: MIT
Keywords: nonebot,nonebot2,genshin,panel,card
Author: monsterxcn
Author-email: monsterxcn@gmail.com
Requires-Python: >=3.8.1,<4.0
Classifier: License :: OSI Approved :: MIT License
Classifier: Programming Language :: Python :: 3
Classifier: Programming Language :: Python :: 3.9
Classifier: Programming Language :: Python :: 3.10
Classifier: Programming Language :: Python :: 3.11
Classifier: Programming Language :: Python :: 3.12
Requires-Dist: attrs (>=20.1.0)
Requires-Dist: httpx (>=0.20.0,<1.0.0)
Requires-Dist: nonebot-adapter-onebot (>=2.0.0b1)
Requires-Dist: nonebot-plugin-htmlrender (>=0.2.1)
Requires-Dist: nonebot2 (>=2.0.0b3)
Requires-Dist: playwright (>=1.25.0)
Project-URL: Documentation, https://github.com/monsterxcn/nonebot-plugin-gspanel#readme
